dockie/__init__.py
dockie/app.tcss
dockie/containers.py
dockie/entrypoint.py
dockie/main.py
dockie-0.1.2.data/data/dockie/app.tcss
dockie-0.1.2.dist-info/METADATA
dockie-0.1.2.dist-info/WHEEL
dockie-0.1.2.dist-info/entry_points.txt
dockie-0.1.2.dist-info/RECORD
