Metadata-Version: 2.4
Name: dockie
Version: 0.1.2
Summary: A Terminal User Interface (TUI) for Docker management built with Textual
Author-email: Kunpeng GUO <kunpeng.guo@the-qa-company.com>
Keywords: containers,docker,terminal,textual,tui
Classifier: Development Status :: 3 - Alpha
Classifier: Environment :: Console
Classifier: Intended Audience :: Developers
Classifier: Intended Audience :: System Administrators
Classifier: License :: OSI Approved :: MIT License
Classifier: Programming Language :: Python :: 3
Classifier: Programming Language :: Python :: 3.12
Classifier: Topic :: System :: Systems Administration
Classifier: Topic :: Terminals
Requires-Python: >=3.11.12
Requires-Dist: docker>=7.0.0
Requires-Dist: fuzzywuzzy>=0.18.0
Requires-Dist: python-levenshtein>=0.21.0
Requires-Dist: textual>=3.3.0
